nside_wefa/__init__.py
nside_wefa/authentication/README.md
nside_wefa/authentication/__init__.py
nside_wefa/authentication/apps.py
nside_wefa/authentication/checks.py
nside_wefa/authentication/constants.py
nside_wefa/authentication/urls.py
nside_wefa/authentication/tests/__init__.py
nside_wefa/authentication/tests/test_apps.py
nside_wefa/authentication/tests/test_checks.py
nside_wefa/authentication/tests/test_urls.py
nside_wefa/authentication/tests/utils/__init__.py
nside_wefa/authentication/tests/utils/test_settings_initialization.py
nside_wefa/authentication/tests/utils/test_utils.py
nside_wefa/authentication/utils/__init__.py
nside_wefa/authentication/utils/settings_initialization.py
nside_wefa/authentication/utils/utils.py
nside_wefa/common/__init__.py
nside_wefa/common/apps.py
nside_wefa/common/checks.py
nside_wefa/common/tests/__init__.py
nside_wefa/common/tests/test_checks.py
nside_wefa/legal_consent/README.md
nside_wefa/legal_consent/__init__.py
nside_wefa/legal_consent/apps.py
nside_wefa/legal_consent/checks.py
nside_wefa/legal_consent/serializers.py
nside_wefa/legal_consent/urls.py
nside_wefa/legal_consent/migrations/0001_initial.py
nside_wefa/legal_consent/migrations/__init__.py
nside_wefa/legal_consent/models/__init__.py
nside_wefa/legal_consent/models/legal_consent.py
nside_wefa/legal_consent/templates/privacy_notice.md
nside_wefa/legal_consent/templates/terms_of_use.md
nside_wefa/legal_consent/templates/en/privacy_notice.md
nside_wefa/legal_consent/templates/en/terms_of_use.md
nside_wefa/legal_consent/test_utils/__init__.py
nside_wefa/legal_consent/tests/__init__.py
nside_wefa/legal_consent/tests/test_checks.py
nside_wefa/legal_consent/tests/migrations/__init__.py
nside_wefa/legal_consent/tests/migrations/test_legal_consent_migration.py
nside_wefa/legal_consent/tests/models/__init__.py
nside_wefa/legal_consent/tests/models/test_legal_consent.py
nside_wefa/legal_consent/tests/serializers/__init__.py
nside_wefa-0.3.0.dist-info/METADATA
nside_wefa-0.3.0.dist-info/WHEEL
nside_wefa-0.3.0.dist-info/RECORD
