Metadata-Version: 2.4
Name: nside-wefa
Version: 0.3.0
Summary: Django library with Legal Consent compliance utilities and reusable apps
Project-URL: Homepage, https://github.com/n-side-dev/wefa
Project-URL: Repository, https://github.com/n-side-dev/wefa
Project-URL: Documentation, https://github.com/n-side-dev/wefa#readme
Project-URL: Issues, https://github.com/n-side-dev/wefa/issues
Author-email: N-SIDE <fso@n-side.com>
License: Apache-2.0
Keywords: api,compliance,django,gdpr,web
Classifier: Development Status :: 3 - Alpha
Classifier: Framework :: Django
Classifier: Framework :: Django :: 5.2
Classifier: Intended Audience :: Developers
Classifier: Operating System :: OS Independent
Classifier: Programming Language :: Python :: 3
Classifier: Programming Language :: Python :: 3.12
Classifier: Programming Language :: Python :: 3.13
Classifier: Topic :: Internet :: WWW/HTTP
Classifier: Topic :: Internet :: WWW/HTTP :: Dynamic Content
Classifier: Topic :: Software Development :: Libraries :: Python Modules
Requires-Python: >=3.12
Requires-Dist: django-cors-headers>=4.9.0
Requires-Dist: django>=5.2.6
Requires-Dist: djangorestframework-simplejwt>=5.5.1
Requires-Dist: djangorestframework>=3.14.0
Requires-Dist: drf-spectacular>=0.28.0
